<?xml version="1.0" encoding="UTF-8"?>
<proxy xmlns="http://ws.apache.org/ns/synapse"
       name="vfsFileStockQuoteProxy"
       transports="vfs"
       startOnLoad="true"
       trace="disable">
   <description/>
   <target>
      <endpoint>
         <address uri="http://localhost:9000/services/SimpleStockQuoteService"
                  format="soap12"/>
      </endpoint>
      <outSequence>
         <property name="transport.vfs.ReplyFileName"
                   expression="fn:concat(fn:substring-after(get-property('MessageID'), 'urn:uuid:'), '.xml')"
                   scope="transport"/>
         <property name="OUT_ONLY" value="true"/>
         <send>
            <endpoint>
               <address uri="vfs:file://C:\Personal\VFS\out"/>
            </endpoint>
         </send>
      </outSequence>
   </target>
   <publishWSDL uri="file:repository/samples/resources/proxy/sample_proxy_1.wsdl"/>
   <parameter name="transport.PollInterval">15</parameter>
   <parameter name="transport.vfs.ActionAfterProcess">MOVE</parameter>
   <parameter name="transport.vfs.FileURI">file://C:\Personal\VFS\Original</parameter>
   <parameter name="transport.vfs.MoveAfterProcess">file://C:\Personal\VFS\Pass</parameter>
   <parameter name="transport.vfs.MoveAfterFailure">file://C:\Personal\VFS\Failures</parameter>
   <parameter name="transport.vfs.FileNamePattern">.*\.xml</parameter>
   <parameter name="transport.vfs.ContentType">text/xml</parameter>
   <parameter name="transport.vfs.ActionAfterFailure">MOVE</parameter>
</proxy>
