<DataTables xmlns:xsi="http://www.w3.org/2001/XMLSchema-instance"
	xsi:noNamespaceSchemaLocation="file://C:/VTAF_TestLink/VTAF/xsd/DataTables.xsd" >
	<Table name="developAPI_CustomAttributeHandling">
		<Header>
			<Column name="tenantOrAdminPublisherOne" type="String" />
			<Column name="domain" type="String" />
			<Column name="adminOrTenantPublisherUserOne" type="String" />
			<Column name="adminOrTenantPublisherUserOnePassword" type="String" />
			<Column name="adminOrTenantOnePublisherUserThree" type="String" />
			<Column name="adminOrTenantOnePublisherUserThreePassword" type="String" />
			<Column name="StoreUserOne" type="String" />
			<Column name="StoreUserOnePassword" type="String" />
			<Column name="APIName" type="String" />
			<Column name="APIContext" type="String" />
			<Column name="APITag" type="String" />
			<Column name="Description" type="String" />
			<Column name="URLPattern" type="String" />
			<Column name="verbMethodGET" type="String" />
			<Column name="ProductionEndPontJaxRS" type="String" />
			<Column name="SandboxEndpoint" type="String" />
			<Column name="ResponseCaching" type="String" />
			<Column name="jasonFileName" type="String" />
			<Column name="APIVersionOne" type="String" />
			<Column name="APIvisibility" type="String" />
			<Column name="APIImageName" type="String" />
			<Column name="urlPatternForPostAndPut" type="String" />
			<Column name="urlPatternForGetDeleteAndHead" type="String" />
			<Column name="cacheTimeForTimeOut" type="String" />
			<Column name="StoreOneOfTenanrOrAdmin" type="String" />
			<Column name="serverNameDomainOne" type="String" />
			<Column name="keywordEnabled" type="String" />
			<Column name="invalidRoleToVisible" type="String" />
			<Column name="numberOfUsersZero" type="String" />
			<Column name="statusPublished" type="String" />
			<Column name="statusCreadted" type="String" />
			<Column name="resourseTierLevel" type="String" />
		</Header>
		<Row>
			<Value>TenantOnePublisherOne</Value>
			<Value>Tenant</Value>
			<Value>keyTenantOnePublisherUserOne</Value>
			<Value>keyTenantOnePublisherOnePassword</Value>
			<Value>keyTenantOnePublisherUserThree</Value>
			<Value>keyTenantOnePublisherThreePassword</Value>
			<Value>keyTenantOneStoreUserOne</Value>
			<Value>keyTenantOneStoreUserOnePassword</Value>
			<Value>APIOne</Value>
			<Value>APIContext</Value>
			<Value>APITag</Value>
			<Value>API Description</Value>
			<Value>say/resource</Value>
			<Value>get</Value>
			<Value>http://localhost:9763/jaxrs_basic/services/customers</Value>
			<Value>http://localhost:9763/jaxrs_basic/services/customers</Value>
			<Value>Enabled</Value>
			<Value>test.json</Value>
			<Value>1.0.0</Value>
			<Value>Public</Value>
			<Value>image1.jpg</Value>
			<Value>/customerservice/customers</Value>
			<Value>/customerservice/customers/{id}</Value>
			<Value>3600</Value>
			<Value>TenantOneStoreOne</Value>
			<Value>TenantOne</Value>
			<Value>Enabled</Value>
			<Value>abcd</Value>
			<Value>0</Value>
			<Value>PUBLISHED</Value>
			<Value>CREATED</Value>
			<Value>Unlimited</Value>
		</Row>
		<Row>
			<Value>AdminPublisherOne</Value>
			<Value>carbon.super</Value>
			<Value>keyAdminPublisherUserOne</Value>
			<Value>keyAdminPublisherUserOnePassword</Value>
			<Value>keyAdminPublisherUserThree</Value>
			<Value>keyAdminPublisherUserThreePassword</Value>
			<Value>keyAdminStoreUserOne</Value>
			<Value>keyAdminStoreUserOnePassword</Value>
			<Value>APIOne</Value>
			<Value>APIContext</Value>
			<Value>APITag</Value>
			<Value>API Description</Value>
			<Value>say/resource</Value>
			<Value>get</Value>
			<Value>http://localhost:9763/jaxrs_basic/services/customers</Value>
			<Value>http://localhost:9763/jaxrs_basic/services/customers</Value>
			<Value>Enabled</Value>
			<Value>test.json</Value>
			<Value>1.0.0</Value>
			<Value>Public</Value>
			<Value>image1.jpg</Value>
			<Value>/customerservice/customers</Value>
			<Value>/customerservice/customers/{id}</Value>
			<Value>3600</Value>
			<Value>AdminStoreOne</Value>
			<Value>Admin</Value>
			<Value>Enabled</Value>
			<Value>abcd</Value>
			<Value>0</Value>
			<Value>PUBLISHED</Value>
			<Value>CREATED</Value>
			<Value>Unlimited</Value>
		</Row>

</Table>
	<Table name="developAPI_DesignNewAPI">
		<Header>
			<Column name="APIName" type="String" />
			<Column name="APIContext" type="String" />
			<Column name="APIVersion" type="String" />
			<Column name="publisherUserOne" type="String" />
			<Column name="adminOrTenantOnePublisherUserOne" type="String" />
			<Column name="adminOrTenantOnePublisherUserOnePassword" type="String" />
			<Column name="storeUserOne" type="String" />
			<Column name="APITagName" type="String" />
		</Header>
		<Row>
			<Value>APIName</Value>
			<Value>APIContext</Value>
			<Value>1.1.1</Value>
			<Value>TenantOnePublisherOne</Value>
			<Value>keyTenantOnePublisherUserOne</Value>
			<Value>keyTenantOnePublisherOnePassword</Value>
			<Value>TenantOneStoreOne</Value>
			<Value>APITagName</Value>
		</Row>
		<Row>
			<Value>APIName</Value>
			<Value>APIContext</Value>
			<Value>1.1.1</Value>
			<Value>AdminPublisherOne</Value>
			<Value>keyAdminPublisherUserOne</Value>
			<Value>keyAdminPublisherUserOnePassword</Value>
			<Value>AdminStoreOne</Value>
			<Value>APITagName</Value>
		</Row>

</Table>
	<Table name="manageAPI_TagManagement">
		<Header>
			<Column name="domain" type="String" />
			<Column name="APIName" type="String" />
			<Column name="APIContext" type="String" />
			<Column name="tag" type="String" />
			<Column name="APIVersion" type="String" />
			<Column name="adminOrTenantOnePublisherUserOne" type="String" />
			<Column name="adminOrTenantOnePublisherUserOnePassword" type="String" />
			<Column name="adminOrTenantOneStoreUserOne" type="String" />
			<Column name="adminOrTenantOneStoreUserOnePassword" type="String" />
			<Column name="productionEndPoint" type="String" />
			<Column name="sandboxEndPoint" type="String" />
		</Header>
		<Row>
			<Value>Tenant</Value>
			<Value>API</Value>
			<Value>/fxx</Value>
			<Value>smack</Value>
			<Value>1.0.0</Value>
			<Value>keyTenantOnePublisherUserOne</Value>
			<Value>keyTenantOnePublisherOnePassword</Value>
			<Value>keyTenantOneStoreUserOne</Value>
			<Value>keyTenantOneStoreUserOnePassword</Value>
			<Value>http://appserver/resource</Value>
			<Value>http://appserver/resource</Value>
		</Row>
		<Row>
			<Value>carbon.super</Value>
			<Value>API</Value>
			<Value>/fxx</Value>
			<Value>smack</Value>
			<Value>1.0.0</Value>
			<Value>keyAdminPublisherUserOne</Value>
			<Value>keyAdminPublisherUserOnePassword</Value>
			<Value>keyAdminStoreUserOne</Value>
			<Value>keyAdminStoreUserOnePassword</Value>
			<Value>http://appserver/resource</Value>
			<Value>http://appserver/resource</Value>
		</Row>

</Table>
	<Table name="APIDocumentation_UpdateDocuments">
		<Header>
			<Column name="domain" type="String" />
			<Column name="apiName" type="String" />
			<Column name="apiContext" type="String" />
			<Column name="apiVersion" type="String" />
			<Column name="docName" type="String" />
			<Column name="ProductionEndPoint" type="String" />
			<Column name="SandBoxEndPoint" type="String" />
			<Column name="sourseUrl" type="String" />
			<Column name="docSummery" type="String" />
			<Column name="docSummeryTwo" type="String" />
			<Column name="APIStatus" type="String" />
			<Column name="adminOrTenantOnePublisherUserOne" type="String" />
			<Column name="adminOrTenantOnePublisherUserOnePassword" type="String" />
			<Column name="adminOrTenantOneStoreUserOne" type="String" />
			<Column name="adminOrTenantOneStoreUserOnePassword" type="String" />
		</Header>
		<Row>
			<Value>Tenant</Value>
			<Value>APIName</Value>
			<Value>APIContext</Value>
			<Value>1.1.1</Value>
			<Value>DocName</Value>
			<Value>http://appserver/resource</Value>
			<Value>http://appserver/resource</Value>
			<Value>https://www.go.com/</Value>
			<Value>test Summery</Value>
			<Value>Summery Two</Value>
			<Value>PUBLISHED</Value>
			<Value>keyTenantOnePublisherUserOne</Value>
			<Value>keyTenantOnePublisherOnePassword</Value>
			<Value>keyTenantOneStoreUserOne</Value>
			<Value>keyTenantOneStoreUserOnePassword</Value>
		</Row>
		<Row>
			<Value>carbon.super</Value>
			<Value>APIName</Value>
			<Value>APIContext</Value>
			<Value>1.1.1</Value>
			<Value>DocName</Value>
			<Value>http://appserver/resource</Value>
			<Value>http://appserver/resource</Value>
			<Value>https://www.go.com/</Value>
			<Value>test Summery</Value>
			<Value>Summery Two</Value>
			<Value>PUBLISHED</Value>
			<Value>keyAdminPublisherUserOne</Value>
			<Value>keyAdminPublisherUserOnePassword</Value>
			<Value>keyAdminStoreUserOne</Value>
			<Value>keyAdminStoreUserOnePassword</Value>
		</Row>

</Table>
	<Table name="APIDocumentation_DocumentVisibility">
		<Header>
			<Column name="domain" type="String" />
			<Column name="adminOrTenantOnePublisherUserOne" type="String" />
			<Column name="adminOrTenantOnePublisherUserOnePassword" type="String" />
			<Column name="adminOrTenantOnePublisherUserTwo" type="String" />
			<Column name="adminOrTenantOnePublisherUserTwoPassword" type="String" />
			<Column name="adminOrTenantOneStoreUserOne" type="String" />
			<Column name="adminOrTenantOneStoreUserOnePassword" type="String" />
			<Column name="adminOrTenantTwoStoreUserOne" type="String" />
			<Column name="adminOrTenantTwoStoreUserOnePassword" type="String" />
			<Column name="adminOrTenantOneStoreUserTwo" type="String" />
			<Column name="adminOrTenantOneStoreUserTwoPassword" type="String" />
			<Column name="APIName" type="String" />
			<Column name="APINameOne" type="String" />
			<Column name="APIVersion" type="String" />
			<Column name="APITagName" type="String" />
			<Column name="APIContext" type="String" />
			<Column name="DocName" type="String" />
			<Column name="DocVisibilitySameAsAPI" type="String" />
			<Column name="DocVisibilityPrivate" type="String" />
			<Column name="DocVisibilityVisibleToMyDomain" type="String" />
			<Column name="APIVisibilityPublic" type="String" />
			<Column name="APIVisibilityVisibleToMyDomain" type="String" />
			<Column name="sandboxEndPoint" type="String" />
			<Column name="productionEndPoint" type="String" />
			<Column name="tenantOne" type="String" />
			<Column name="tenantTwo" type="String" />
			<Column name="imageName" type="String" />
			<Column name="tagName" type="String" />
			<Column name="keyWordDoc" type="String" />
			<Column name="documentNameDocOne" type="String" />
			<Column name="documentSummeryDocOne" type="String" />
			<Column name="keyWordViewContent" type="String" />
			<Column name="searchForDocumentKeyWordHello" type="String" />
			<Column name="noMatchingResults" type="String" />
			<Column name="keyWordAnonimous" type="String" />
			<Column name="docSearchKeyWord" type="String" />
			<Column name="docSearchKeyWordTwo" type="String" />
			<Column name="SourceURL" type="String" />
			<Column name="docSearchKeyWordThree" type="String" />
		</Header>
		<Row>
			<Value>TenantOne</Value>
			<Value>keyTenantOnePublisherUserOne</Value>
			<Value>keyTenantOnePublisherOnePassword</Value>
			<Value>keyTenantOnePublisherUserTwo</Value>
			<Value>keyTenantOnePublisherTwoPassword</Value>
			<Value>keyTenantOneStoreUserOne</Value>
			<Value>keyTenantOneStoreUserOnePassword</Value>
			<Value>keyTenantTwoStoreUserOne</Value>
			<Value>keyTenantTwoStoreUserOnePassword</Value>
			<Value>keyTenantOneStoreUserTwo</Value>
			<Value>keyTenantOneStoreUserTwoPassword</Value>
			<Value>API</Value>
			<Value>API1</Value>
			<Value>1.1.1</Value>
			<Value>APITagName</Value>
			<Value>APIContext</Value>
			<Value>DocName</Value>
			<Value>Same as API visibility</Value>
			<Value>Private</Value>
			<Value>Visible to my domain</Value>
			<Value>Public</Value>
			<Value>Visible to my domain</Value>
			<Value>http://localhost:9763/jaxrs_basic/services/customers</Value>
			<Value>http://localhost:9763/jaxrs_basic/services/customers</Value>
			<Value>TenantOne</Value>
			<Value>TenantTwo</Value>
			<Value>test.jpeg</Value>
			<Value>test_tag</Value>
			<Value>doc:</Value>
			<Value>doc1</Value>
			<Value>summary of doc one</Value>
			<Value>View Content</Value>
			<Value>doc:hello</Value>
			<Value>No matching results</Value>
			<Value>TenantTwo</Value>
			<Value>doc:hello</Value>
			<Value>hello</Value>
			<Value>www.facebook.com</Value>
			<Value>doc:facebook</Value>
		</Row>
		<Row>
			<Value>Admin</Value>
			<Value>keyAdminPublisherUserOne</Value>
			<Value>keyAdminPublisherUserOnePassword</Value>
			<Value>keyAdminPublisherUserTwo</Value>
			<Value>keyAdminPublisherUserTwoPassword</Value>
			<Value>keyAdminStoreUserOne</Value>
			<Value>keyAdminStoreUserOnePassword</Value>
			<Value>keyTenantTwoStoreUserOne</Value>
			<Value>keyTenantTwoStoreUserOnePassword</Value>
			<Value>keyAdminStoreUserTwo</Value>
			<Value>keyAdminStoreUserTwoPassword</Value>
			<Value>API</Value>
			<Value>API1</Value>
			<Value>1.1.1</Value>
			<Value>APITagName</Value>
			<Value>APIContext</Value>
			<Value>DocName</Value>
			<Value>Same as API visibility</Value>
			<Value>Private</Value>
			<Value>Visible to my domain</Value>
			<Value>Public</Value>
			<Value>Visible to my domain</Value>
			<Value>http://localhost:9763/jaxrs_basic/services/customers</Value>
			<Value>http://localhost:9763/jaxrs_basic/services/customers</Value>
			<Value>Admin</Value>
			<Value>Admin</Value>
			<Value>test.jpeg</Value>
			<Value>test_tag</Value>
			<Value>doc:</Value>
			<Value>doc1</Value>
			<Value>summary of doc one</Value>
			<Value>View Content</Value>
			<Value>doc:hello</Value>
			<Value>No matching results</Value>
			<Value>TenantTwo</Value>
			<Value>doc:hello</Value>
			<Value>hello</Value>
			<Value>www.facebook.com</Value>
			<Value>doc:facebook</Value>
		</Row>

</Table>
	<Table name="testCasesWith_FireEvents">
		<Header>
			<Column name="adminOrTenantOnePublisherUserOne" type="String" />
			<Column name="adminOrTenantOnePublisherUserOnePassword" type="String" />
			<Column name="adminOrTenantOneStoreUserOne" type="String" />
			<Column name="adminOrTenantOneStoreUserOnePassword" type="String" />
			<Column name="apiName" type="String" />
			<Column name="apiVersion" type="String" />
			<Column name="apiTagName" type="String" />
			<Column name="apiContext" type="String" />
			<Column name="downImag" type="String" />
			<Column name="downloadFilePathSwagger" type="String" />
			<Column name="downloadFilePathJson" type="String" />
		</Header>
		<Row>
			<Value>keyTenantOnePublisherUserOne</Value>
			<Value>keyTenantOnePublisherOnePassword</Value>
			<Value>keyTenantOneStoreUserOne</Value>
			<Value>keyTenantOneStoreUserOnePassword</Value>
			<Value>APIName</Value>
			<Value>1.1.1</Value>
			<Value>ApiTagName</Value>
			<Value>APIContext</Value>
			<Value>DownloadPopupOne.JPG</Value>
			<Value>C:\\Users\\jwickramarathne\\Downloads\\swagger.yaml</Value>
			<Value>C:\\Users\\jwickramarathne\\Downloads\\swagger.json</Value>
		</Row>
		<Row>
			<Value>keyAdminPublisherUserOne</Value>
			<Value>keyAdminPublisherUserOnePassword</Value>
			<Value>keyAdminStoreUserOne</Value>
			<Value>keyAdminStoreUserOnePassword</Value>
			<Value>APIName</Value>
			<Value>1.1.1</Value>
			<Value>ApiTagName</Value>
			<Value>APIContext</Value>
			<Value>DownloadPopupOne.JPG</Value>
			<Value>C:\\Users\\jwickramarathne\\Downloads\\swagger.yaml</Value>
			<Value>C:\\Users\\jwickramarathne\\Downloads\\swagger.json</Value>
		</Row>

</Table>
	<Table name="tierManagement_TierPermission">
		<Header>
			<Column name="APIName" type="String" />
			<Column name="apiContext" type="String" />
			<Column name="apiVersionOne" type="String" />
			<Column name="apiVisibilityPublic" type="String" />
			<Column name="apiImageName" type="String" />
			<Column name="tagName" type="String" />
			<Column name="urlPatternForPostAndPut" type="String" />
			<Column name="urlPatternForGetDeleteAndHead" type="String" />
			<Column name="productionEndpoint" type="String" />
			<Column name="internalOrEveryoneKeyWord" type="String" />
			<Column name="tenantOneOfDomainOne" type="String" />
			<Column name="publisherOneOfTenentOneOrAdmin" type="String" />
			<Column name="publisherTwoOfTenentOneOrAdmin" type="String" />
			<Column name="storeOneOfTenanrOrAdmin" type="String" />
			<Column name="storeTwoOfTenanrOrAdmin" type="String" />
			<Column name="storeThreeOfTenanrOrAdmin" type="String" />
			<Column name="storeFourOfTenanrOrAdmin" type="String" />
			<Column name="storeFiveOfTenanrOrAdmin" type="String" />
			<Column name="storeSixOfTenanrOrAdmin" type="String" />
			<Column name="tierNameGold" type="String" />
			<Column name="tierNameSilver" type="String" />
			<Column name="tierNameBronze" type="String" />
			<Column name="tierNameUnlimited" type="String" />
			<Column name="tierNameCustom" type="String" />
			<Column name="wrongRole" type="String" />
			<Column name="errorMessageInvalidRoleName" type="String" />
			<Column name="errorMessageThisFieldIsRequired" type="String" />
		</Header>
		<Row>
			<Value>api</Value>
			<Value>context</Value>
			<Value>1.0.0</Value>
			<Value>Public</Value>
			<Value>image1.jpg</Value>
			<Value>tag</Value>
			<Value>/customerservice/customers</Value>
			<Value>/customerservice/customers/{id}</Value>
			<Value>http://localhost:9763/jaxrs_basic/services/customers</Value>
			<Value>Internal/everyone</Value>
			<Value>TenantOne</Value>
			<Value>TenantOnePublisherOne</Value>
			<Value>TenantOnePublisherTwo</Value>
			<Value>TenantOneStoreOne</Value>
			<Value>TenantOneStoreTwo</Value>
			<Value>TenantOneStoreThree</Value>
			<Value>TenantOneStoreFour</Value>
			<Value>TenantOneStoreFive</Value>
			<Value>TenantOneStoreSix</Value>
			<Value>Gold</Value>
			<Value>Silver</Value>
			<Value>Bronze</Value>
			<Value>Unlimited</Value>
			<Value>Custom</Value>
			<Value>cccc</Value>
			<Value>Invalid role name</Value>
			<Value>This field is required</Value>
		</Row>
		<Row>
			<Value>api</Value>
			<Value>context</Value>
			<Value>1.0.0</Value>
			<Value>Public</Value>
			<Value>image1.jpg</Value>
			<Value>tag</Value>
			<Value>/customerservice/customers</Value>
			<Value>/customerservice/customers/{id}</Value>
			<Value>http://localhost:9763/jaxrs_basic/services/customers</Value>
			<Value>Internal/everyone</Value>
			<Value>Admin</Value>
			<Value>AdminPublisherOne</Value>
			<Value>AdminPublisherTwo</Value>
			<Value>AdminStoreOne</Value>
			<Value>AdminStoreTwo</Value>
			<Value>AdminStoreFour</Value>
			<Value>AdminStoreFive</Value>
			<Value>AdminStoreSix</Value>
			<Value>AdminStoreSeven</Value>
			<Value>Gold</Value>
			<Value>Silver</Value>
			<Value>Bronze</Value>
			<Value>Unlimited</Value>
			<Value>Custom</Value>
			<Value>cccc</Value>
			<Value>Invalid role name</Value>
			<Value>This field is required</Value>
		</Row>

</Table>
	<Table name="APIVersioning_PluggableVersionContext">
		<Header>
			<Column name="apiName" type="String" />
			<Column name="apiContext" type="String" />
			<Column name="apiVersionOne" type="String" />
			<Column name="apiVersionTwo" type="String" />
			<Column name="apiVisibilityPublic" type="String" />
			<Column name="apiImage" type="String" />
			<Column name="apiTagName" type="String" />
			<Column name="productionEndpoint" type="String" />
			<Column name="sandboxEndpoint" type="String" />
			<Column name="numberOfUsersZero" type="String" />
			<Column name="statusCreated" type="String" />
			<Column name="statusPublished" type="String" />
			<Column name="statusDeprecated" type="String" />
			<Column name="publisherOneOfTenantOneOrAdmin" type="String" />
			<Column name="storeOneOfTenantOneOrAdmin" type="String" />
			<Column name="serverNameDomainOne" type="String" />
			<Column name="urlPatternForPostAndPut" type="String" />
			<Column name="urlPatternForGetDeleteAndHead" type="String" />
			<Column name="applicationName" type="String" />
			<Column name="applicationDiscription" type="String" />
			<Column name="keyTypeToInvoke" type="String" />
			<Column name="postPayloadContext" type="String" />
			<Column name="postCustomerNameFromPayloadContext" type="String" />
			<Column name="postResponseHeaders" type="String" />
			<Column name="getCustomerName" type="String" />
			<Column name="getResponseHeaders" type="String" />
			<Column name="putCustomerName" type="String" />
			<Column name="getCustomerNameForPutVerification" type="String" />
			<Column name="getResponseHeadersForPutVerification" type="String" />
			<Column name="deleteResponseHeaders" type="String" />
			<Column name="invokeTypeProduction" type="String" />
			<Column name="invokeTypeSandbox" type="String" />
			<Column name="tierType" type="String" />
			<Column name="numberOfUsersOne" type="String" />
		</Header>
		<Row>
			<Value>api</Value>
			<Value>context</Value>
			<Value>1.0.0</Value>
			<Value>2.0.0</Value>
			<Value>Public</Value>
			<Value>image1.jpg</Value>
			<Value>tag</Value>
			<Value>http://localhost:9763/jaxrs_basic/services/customers</Value>
			<Value>http://localhost:9763/jaxrs_basic/services/customers</Value>
			<Value>0</Value>
			<Value>CREATED</Value>
			<Value>PUBLISHED</Value>
			<Value>DEPRECATED</Value>
			<Value>TenantOnePublisherOne</Value>
			<Value>TenantOneStoreOne</Value>
			<Value>TenantOne</Value>
			<Value>/customerservice/customers</Value>
			<Value>/customerservice/customers/{id}</Value>
			<Value>DefaultApplication</Value>
			<Value>desc</Value>
			<Value>Production</Value>
			<Value>{&quot;Customer&quot;:{&quot;name&quot;:&quot;Kumar&quot;}}</Value>
			<Value>Kumar</Value>
			<Value>application/json</Value>
			<Value>Kumar</Value>
			<Value>application/json</Value>
			<Value>Sangakara</Value>
			<Value>Sangakara</Value>
			<Value>application/json</Value>
			<Value>application/octet-stream</Value>
			<Value>Production</Value>
			<Value>Sandbox</Value>
			<Value>Unlimited</Value>
			<Value>1</Value>
		</Row>
		<Row>
			<Value>api</Value>
			<Value>context</Value>
			<Value>1.0.0</Value>
			<Value>2.0.0</Value>
			<Value>Public</Value>
			<Value>image1.jpg</Value>
			<Value>tag</Value>
			<Value>http://localhost:9763/jaxrs_basic/services/customers</Value>
			<Value>http://localhost:9763/jaxrs_basic/services/customers</Value>
			<Value>0</Value>
			<Value>CREATED</Value>
			<Value>PUBLISHED</Value>
			<Value>DEPRECATED</Value>
			<Value>AdminPublisherOne</Value>
			<Value>AdminStoreOne</Value>
			<Value>Admin</Value>
			<Value>/customerservice/customers</Value>
			<Value>/customerservice/customers/{id}</Value>
			<Value>DefaultApplication</Value>
			<Value>desc</Value>
			<Value>Production</Value>
			<Value>{&quot;Customer&quot;:{&quot;name&quot;:&quot;Kumar&quot;}}</Value>
			<Value>Kumar</Value>
			<Value>application/json</Value>
			<Value>Kumar</Value>
			<Value>application/json</Value>
			<Value>Sangakara</Value>
			<Value>Sangakara</Value>
			<Value>application/json</Value>
			<Value>application/octet-stream</Value>
			<Value>Production</Value>
			<Value>Sandbox</Value>
			<Value>Unlimited</Value>
			<Value>1</Value>
		</Row>

</Table>
	<Table name="APIVersioning_Default_Version">
		<Header>
			<Column name="apiName" type="String" />
			<Column name="apiContext" type="String" />
			<Column name="apiVersionOne" type="String" />
			<Column name="apiVersionTwo" type="String" />
			<Column name="apiVersionThree" type="String" />
			<Column name="apiVersionFour" type="String" />
			<Column name="apiVersionFive" type="String" />
			<Column name="apiVisibilityPublic" type="String" />
			<Column name="apiImage" type="String" />
			<Column name="apiTagName" type="String" />
			<Column name="productionEndpoint" type="String" />
			<Column name="sandboxEndpoint" type="String" />
			<Column name="numberOfUsersZero" type="String" />
			<Column name="statusCreated" type="String" />
			<Column name="statusPublished" type="String" />
			<Column name="statusDeprecated" type="String" />
			<Column name="publisherOneOfTenantOneOrAdmin" type="String" />
			<Column name="adminOrTenantOnePublisherUserOne" type="String" />
			<Column name="adminOrTenantOnePublisherOnePassword" type="String" />
			<Column name="storeOneOfTenantOneOrAdmin" type="String" />
			<Column name="adminOrTenantOneStoreUserOne" type="String" />
			<Column name="adminOrTenantOneStoreUserOnePassword" type="String" />
			<Column name="serverNameDomainOne" type="String" />
			<Column name="urlPatternForPostAndPut" type="String" />
			<Column name="urlPatternForGetDeleteAndHead" type="String" />
			<Column name="applicationName" type="String" />
			<Column name="applicationDiscription" type="String" />
			<Column name="keyTypeToInvoke" type="String" />
			<Column name="postPayloadContext" type="String" />
			<Column name="postCustomerNameFromPayloadContext" type="String" />
			<Column name="postResponseHeaders" type="String" />
			<Column name="getCustomerName" type="String" />
			<Column name="getResponseHeaders" type="String" />
			<Column name="putCustomerName" type="String" />
			<Column name="getCustomerNameForPutVerification" type="String" />
			<Column name="getResponseHeadersForPutVerification" type="String" />
			<Column name="deleteResponseHeaders" type="String" />
			<Column name="DefaultApplication" type="String" />
		</Header>
		<Row>
			<Value>api</Value>
			<Value>context</Value>
			<Value>1.0.0</Value>
			<Value>2.0.0</Value>
			<Value>3.0.0</Value>
			<Value>4.0.0</Value>
			<Value>5.0.0</Value>
			<Value>Public</Value>
			<Value>image1.jpg</Value>
			<Value>tag</Value>
			<Value>http://localhost:9763/jaxrs_basic/services/customers</Value>
			<Value>http://localhost:9763/jaxrs_basic/services/customers</Value>
			<Value>0</Value>
			<Value>CREATED</Value>
			<Value>PUBLISHED</Value>
			<Value>DEPRECATED</Value>
			<Value>TenantOnePublisherOne</Value>
			<Value>keyTenantOnePublisherUserOne</Value>
			<Value>keyTenantOnePublisherOnePassword</Value>
			<Value>TenantOneStoreOne</Value>
			<Value>keyTenantOneStoreUserOne</Value>
			<Value>keyTenantOneStoreUserOnePassword</Value>
			<Value>TenantOne</Value>
			<Value>/customerservice/customers</Value>
			<Value>/customerservice/customers/{id}</Value>
			<Value>app</Value>
			<Value>desc</Value>
			<Value>Production</Value>
			<Value>{&quot;Customer&quot;:{&quot;name&quot;:&quot;Kumar&quot;}}</Value>
			<Value>Kumar</Value>
			<Value>application/json</Value>
			<Value>Kumar</Value>
			<Value>application/json</Value>
			<Value>Sangakara</Value>
			<Value>Sangakara</Value>
			<Value>application/json</Value>
			<Value>application/octet-stream</Value>
			<Value>DefaultApplication</Value>
		</Row>
		<Row>
			<Value>api</Value>
			<Value>context</Value>
			<Value>1.0.0</Value>
			<Value>2.0.0</Value>
			<Value>3.0.0</Value>
			<Value>4.0.0</Value>
			<Value>5.0.0</Value>
			<Value>Public</Value>
			<Value>image1.jpg</Value>
			<Value>tag</Value>
			<Value>http://localhost:9763/jaxrs_basic/services/customers</Value>
			<Value>http://localhost:9763/jaxrs_basic/services/customers</Value>
			<Value>0</Value>
			<Value>CREATED</Value>
			<Value>PUBLISHED</Value>
			<Value>DEPRECATED</Value>
			<Value>AdminPublisherOne</Value>
			<Value>keyAdminPublisherUserOne</Value>
			<Value>keyAdminPublisherUserOnePassword</Value>
			<Value>AdminStoreOne</Value>
			<Value>keyAdminStoreUserOne</Value>
			<Value>keyAdminStoreUserOnePassword</Value>
			<Value>Admin</Value>
			<Value>/customerservice/customers</Value>
			<Value>/customerservice/customers/{id}</Value>
			<Value>app</Value>
			<Value>desc</Value>
			<Value>Production</Value>
			<Value>{&quot;Customer&quot;:{&quot;name&quot;:&quot;Kumar&quot;}}</Value>
			<Value>Kumar</Value>
			<Value>application/json</Value>
			<Value>Kumar</Value>
			<Value>application/json</Value>
			<Value>Sangakara</Value>
			<Value>Sangakara</Value>
			<Value>application/json</Value>
			<Value>application/octet-stream</Value>
			<Value>DefaultApplication</Value>
		</Row>

</Table>
	<Table name="APIVersioning_WithoutDefaultVersion">
		<Header>
			<Column name="apiName" type="String" />
			<Column name="apiContext" type="String" />
			<Column name="apiVersionOne" type="String" />
			<Column name="apiVersionTwo" type="String" />
			<Column name="apiVisibilityPublic" type="String" />
			<Column name="apiImage" type="String" />
			<Column name="apiTagName" type="String" />
			<Column name="productionEndpoint" type="String" />
			<Column name="sandboxEndpoint" type="String" />
			<Column name="numberOfUsersZero" type="String" />
			<Column name="statusCreated" type="String" />
			<Column name="statusPublished" type="String" />
			<Column name="statusDeprecated" type="String" />
			<Column name="publisherOneOfTenantOneOrAdmin" type="String" />
			<Column name="adminOrTenantOnePublisherUserOne" type="String" />
			<Column name="adminOrTenantOnePublisherOnePassword" type="String" />
			<Column name="storeOneOfTenantOneOrAdmin" type="String" />
			<Column name="serverNameDomainOne" type="String" />
			<Column name="urlPatternForPostAndPut" type="String" />
			<Column name="urlPatternForGetDeleteAndHead" type="String" />
			<Column name="applicationName" type="String" />
			<Column name="applicationDiscription" type="String" />
			<Column name="keyTypeToInvoke" type="String" />
			<Column name="postPayloadContext" type="String" />
			<Column name="postCustomerNameFromPayloadContext" type="String" />
			<Column name="postResponseHeaders" type="String" />
			<Column name="getCustomerName" type="String" />
			<Column name="getResponseHeaders" type="String" />
			<Column name="putCustomerName" type="String" />
			<Column name="getCustomerNameForPutVerification" type="String" />
			<Column name="getResponseHeadersForPutVerification" type="String" />
			<Column name="deleteResponseHeaders" type="String" />
			<Column name="invokeTypeProduction" type="String" />
			<Column name="invokeTypeSandbox" type="String" />
			<Column name="tierType" type="String" />
			<Column name="numberOfUsersOne" type="String" />
		</Header>
		<Row>
			<Value>api</Value>
			<Value>context</Value>
			<Value>1.0.0</Value>
			<Value>2.0.0</Value>
			<Value>Public</Value>
			<Value>image1.jpg</Value>
			<Value>tag</Value>
			<Value>http://localhost:9763/jaxrs_basic/services/customers</Value>
			<Value>http://localhost:9763/jaxrs_basic/services/customers</Value>
			<Value>0</Value>
			<Value>CREATED</Value>
			<Value>PUBLISHED</Value>
			<Value>DEPRECATED</Value>
			<Value>TenantOnePublisherOne</Value>
			<Value>keyTenantOnePublisherUserOne</Value>
			<Value>keyTenantOnePublisherOnePassword</Value>
			<Value>TenantOneStoreOne</Value>
			<Value>TenantOne</Value>
			<Value>/customerservice/customers</Value>
			<Value>/customerservice/customers/{id}</Value>
			<Value>DefaultApplication</Value>
			<Value>desc</Value>
			<Value>Production</Value>
			<Value>{&quot;Customer&quot;:{&quot;name&quot;:&quot;Kumar&quot;}}</Value>
			<Value>Kumar</Value>
			<Value>application/json</Value>
			<Value>Kumar</Value>
			<Value>application/json</Value>
			<Value>Sangakara</Value>
			<Value>Sangakara</Value>
			<Value>application/json</Value>
			<Value>application/octet-stream</Value>
			<Value>Production</Value>
			<Value>Sandbox</Value>
			<Value>Unlimited</Value>
			<Value>1</Value>
		</Row>
		<Row>
			<Value>api</Value>
			<Value>context</Value>
			<Value>1.0.0</Value>
			<Value>2.0.0</Value>
			<Value>Public</Value>
			<Value>image1.jpg</Value>
			<Value>tag</Value>
			<Value>http://localhost:9763/jaxrs_basic/services/customers</Value>
			<Value>http://localhost:9763/jaxrs_basic/services/customers</Value>
			<Value>0</Value>
			<Value>CREATED</Value>
			<Value>PUBLISHED</Value>
			<Value>DEPRECATED</Value>
			<Value>AdminPublisherOne</Value>
			<Value>keyAdminPublisherUserOne</Value>
			<Value>keyAdminPublisherUserOnePassword</Value>
			<Value>AdminStoreOne</Value>
			<Value>Admin</Value>
			<Value>/customerservice/customers</Value>
			<Value>/customerservice/customers/{id}</Value>
			<Value>DefaultApplication</Value>
			<Value>desc</Value>
			<Value>Production</Value>
			<Value>{&quot;Customer&quot;:{&quot;name&quot;:&quot;Kumar&quot;}}</Value>
			<Value>Kumar</Value>
			<Value>application/json</Value>
			<Value>Kumar</Value>
			<Value>application/json</Value>
			<Value>Sangakara</Value>
			<Value>Sangakara</Value>
			<Value>application/json</Value>
			<Value>application/octet-stream</Value>
			<Value>Production</Value>
			<Value>Sandbox</Value>
			<Value>Unlimited</Value>
			<Value>1</Value>
		</Row>

</Table>
	<Table name="APIVersioning_LifeCycle">
		<Header>
			<Column name="APIVersion" type="String" />
			<Column name="APIName" type="String" />
			<Column name="newVersionOne" type="String" />
			<Column name="stateCreated" type="String" />
			<Column name="statePrototyped" type="String" />
			<Column name="APIContext" type="String" />
			<Column name="publisherOneOfTenantOneOrAdmin" type="String" />
			<Column name="StoreOneOfTenantOneOrAdmin" type="String" />
			<Column name="adminOrTenantOnePublisherUserOne" type="String" />
			<Column name="adminOrTenantOnePublisherUserOnePassword" type="String" />
			<Column name="productionEndpoint" type="String" />
		</Header>
		<Row>
			<Value>1.0.0</Value>
			<Value>Api1mm</Value>
			<Value>1.0.1</Value>
			<Value>CREATED</Value>
			<Value>PROTOTYPED</Value>
			<Value>context</Value>
			<Value>TenantOnePublisherOne</Value>
			<Value>TenantOneStoreOne</Value>
			<Value>keyTenantOnePublisherUserOne</Value>
			<Value>keyTenantOnePublisherOnePassword</Value>
			<Value>http://localhost:9763/jaxrs_basic/services/customers</Value>
		</Row>
		<Row>
			<Value>1.0.0</Value>
			<Value>Api1mm</Value>
			<Value>1.0.1</Value>
			<Value>CREATED</Value>
			<Value>PROTOTYPED</Value>
			<Value>context</Value>
			<Value>AdminPublisherOne</Value>
			<Value>AdminStoreOne</Value>
			<Value>keyAdminPublisherUserOne</Value>
			<Value>keyAdminPublisherUserOnePassword</Value>
			<Value>http://localhost:9763/jaxrs_basic/services/customers</Value>
		</Row>

</Table>
	<Table name="keyWords">
		<Header>
			<Column name="keyWordYes" type="String" />
			<Column name="keyWordNo" type="String" />
			<Column name="keyWordPost" type="String" />
			<Column name="keyWordPatch" type="String" />
			<Column name="keyWordGet" type="String" />
			<Column name="keyWordPut" type="String" />
			<Column name="keyWordHead" type="String" />
			<Column name="keyWordDelete" type="String" />
			<Column name="numericValueTwoHundred" type="String" />
			<Column name="numericValueTwoHundredAndFour" type="String" />
			<Column name="numericValueOne" type="String" />
			<Column name="numericValueTwo" type="String" />
			<Column name="keyWordNull" type="String" />
			<Column name="keyWordNoContent" type="String" />
			<Column name="keyWordTrue" type="String" />
			<Column name="keyWordFalse" type="String" />
		</Header>
		<Row>
			<Value>yes</Value>
			<Value>no</Value>
			<Value>post</Value>
			<Value>patch</Value>
			<Value>get</Value>
			<Value>put</Value>
			<Value>head</Value>
			<Value>delete</Value>
			<Value>200</Value>
			<Value>204</Value>
			<Value>1</Value>
			<Value>2</Value>
			<Value>null</Value>
			<Value>no content</Value>
			<Value>true</Value>
			<Value>false</Value>
		</Row>
		<Row>
			<Value>yes</Value>
			<Value>no</Value>
			<Value>post</Value>
			<Value>patch</Value>
			<Value>get</Value>
			<Value>put</Value>
			<Value>head</Value>
			<Value>delete</Value>
			<Value>200</Value>
			<Value>204</Value>
			<Value>1</Value>
			<Value>2</Value>
			<Value>null</Value>
			<Value>no content</Value>
			<Value>true</Value>
			<Value>false</Value>
		</Row>

</Table>
	<Table name="pauseTimes">
		<Header>
			<Column name="oneSecond" type="String" />
			<Column name="twoSeconds" type="String" />
			<Column name="threeSeconds" type="String" />
			<Column name="fourSeconds" type="String" />
			<Column name="fiveSeconds" type="String" />
			<Column name="sixSeconds" type="String" />
			<Column name="sevenSeconds" type="String" />
			<Column name="eightSeconds" type="String" />
			<Column name="nineSeconds" type="String" />
			<Column name="tenSeconds" type="String" />
			<Column name="elevenSeconds" type="String" />
			<Column name="twelveSeconds" type="String" />
			<Column name="thirteenSeconds" type="String" />
			<Column name="fourteenSeconds" type="String" />
			<Column name="fifteenSeconds" type="String" />
		</Header>
		<Row>
			<Value>1000</Value>
			<Value>2000</Value>
			<Value>3000</Value>
			<Value>4000</Value>
			<Value>5000</Value>
			<Value>6000</Value>
			<Value>7000</Value>
			<Value>8000</Value>
			<Value>9000</Value>
			<Value>10000</Value>
			<Value>11000</Value>
			<Value>12000</Value>
			<Value>13000</Value>
			<Value>14000</Value>
			<Value>15000</Value>
		</Row>
		<Row>
			<Value>1000</Value>
			<Value>2000</Value>
			<Value>3000</Value>
			<Value>4000</Value>
			<Value>5000</Value>
			<Value>6000</Value>
			<Value>7000</Value>
			<Value>8000</Value>
			<Value>9000</Value>
			<Value>10000</Value>
			<Value>11000</Value>
			<Value>12000</Value>
			<Value>13000</Value>
			<Value>14000</Value>
			<Value>15000</Value>
		</Row>

</Table>
	<Table name="URLs">
		<Header>
			<Column name="carbonURL" type="String" />
			<Column name="publisherURL" type="String" />
			<Column name="storeURL" type="String" />
		</Header>
		<Row>
			<Value>https://localhost:9443/carbon/admin/login.jsp</Value>
			<Value>https://localhost:9443/publisher/</Value>
			<Value>https://localhost:9443/store/</Value>
		</Row>
		<Row>
			<Value>https://localhost:9443/carbon/admin/login.jsp</Value>
			<Value>https://localhost:9443/publisher/</Value>
			<Value>https://localhost:9443/store/</Value>
		</Row>

</Table>
	<Table name="common">
		<Header>
			<Column name="superAdminUserName" type="String" />
			<Column name="superAdminPassword" type="String" />
			<Column name="carbonURL" type="String" />
			<Column name="PublisherURL" type="String" />
			<Column name="storeURL" type="String" />
		</Header>
		<Row>
			<Value>admin</Value>
			<Value>admin</Value>
			<Value>https://localhost:9443/carbon/admin/login.jsp</Value>
			<Value>https://localhost:9443/publisher/</Value>
			<Value>https://localhost:9443/store/</Value>
		</Row>

</Table>
	<Table name="tenant_UserCreation">
		<Header>
			<Column name="tenantOnePublisherUserNameOne" type="String" />
			<Column name="tenantOnePublisherUserOnePassword" type="String" />
			<Column name="tenantOneRoleNameOnePublisherUserOne" type="String" />
			<Column name="tenantOneStoreUserNameOne" type="String" />
			<Column name="tenantOneStoreUserOnePassword" type="String" />
			<Column name="tenantOneRoleNameOneStoreUserOne" type="String" />
			<Column name="tenantOnePublisherUserNameTwo" type="String" />
			<Column name="tenantOnePublisherUserTwoPassword" type="String" />
			<Column name="tenantOneRoleNameOnePublisherUserTwo" type="String" />
			<Column name="tenantOnePublisherUserNameThree" type="String" />
			<Column name="tenantOnePublisherUserThreePassword" type="String" />
			<Column name="tenantOneRoleNameOnePublisherUserThree" type="String" />
			<Column name="tenantOneStoreUserNameTwo" type="String" />
			<Column name="tenantOneStoreUserTwoPassword" type="String" />
			<Column name="tenantOneRoleNameOneStoreUserTwo" type="String" />
			<Column name="tenantOneRoleNameThreeStoreUserThree" type="String" />
			<Column name="tenantOneStoreUserNameThree" type="String" />
			<Column name="tenantOneStoreUserThreePassword" type="String" />
			<Column name="tenantOneRoleNameFourStoreUserFour" type="String" />
			<Column name="tenantOneStoreUserNameFour" type="String" />
			<Column name="tenantOneStoreUserFourPassword" type="String" />
			<Column name="tenantOneRoleNameFiveStoreUserFive" type="String" />
			<Column name="tenantOneStoreUserNameFive" type="String" />
			<Column name="tenantOneStoreUserFivePassword" type="String" />
			<Column name="tenantOneStoreUserNameSix" type="String" />
			<Column name="tenantOneStoreUserSixPassword" type="String" />
			<Column name="tenantTwoPublisherUserNameOne" type="String" />
			<Column name="tenantTwoPublisherUserOnePassword" type="String" />
			<Column name="tenantTwoRoleNameOnePublisherUserOne" type="String" />
			<Column name="tenantTwoStoreUserNameOne" type="String" />
			<Column name="tenantTwoStoreUserOnePassword" type="String" />
			<Column name="tenantTwoRoleNameOneStoreUserOne" type="String" />
			<Column name="tenantThreePublisherUserNameOne" type="String" />
			<Column name="tenantThreePublisherUserOnePassword" type="String" />
			<Column name="tenantThreeRoleNameOnePublisherUserOne" type="String" />
			<Column name="tenantThreeStoreUserNameOne" type="String" />
			<Column name="tenantThreeStoreUserOnePassword" type="String" />
			<Column name="tenantThreeRoleNameOneStoreUserOne" type="String" />
			<Column name="tenantThreeStoreUserNameTwo" type="String" />
			<Column name="tenantThreeStoreUserTwoPassword" type="String" />
			<Column name="tenantThreeRoleNameOneStoreUserTwo" type="String" />
			<Column name="twoSeconds" type="String" />
			<Column name="fourSeconds" type="String" />
			<Column name="sixSeconds" type="String" />
			<Column name="eightSeconds" type="String" />
		</Header>
		<Row>
			<Value>t1p1</Value>
			<Value>111111</Value>
			<Value>t1p1r1</Value>
			<Value>t1s1</Value>
			<Value>111111</Value>
			<Value>s1r1</Value>
			<Value>t1p2</Value>
			<Value>111111</Value>
			<Value>t1p2r1</Value>
			<Value>t1p3</Value>
			<Value>111111</Value>
			<Value>t1p3r1</Value>
			<Value>t1s2</Value>
			<Value>111111</Value>
			<Value>t1s2r1</Value>
			<Value>t1s3r3</Value>
			<Value>t1s3</Value>
			<Value>111111</Value>
			<Value>t1s4r4</Value>
			<Value>t1s4</Value>
			<Value>111111</Value>
			<Value>t1s5r5</Value>
			<Value>t1s5</Value>
			<Value>111111</Value>
			<Value>t1s6</Value>
			<Value>111111</Value>
			<Value>t2p2</Value>
			<Value>111111</Value>
			<Value>t2p1r1</Value>
			<Value>t2s1</Value>
			<Value>111111</Value>
			<Value>s1r1</Value>
			<Value>t3p1</Value>
			<Value>111111</Value>
			<Value>t3p1r1</Value>
			<Value>t3s1</Value>
			<Value>111111</Value>
			<Value>t3s1r1</Value>
			<Value>t3s2</Value>
			<Value>111111</Value>
			<Value>t3s1r2</Value>
			<Value>2000</Value>
			<Value>4000</Value>
			<Value>6000</Value>
			<Value>8000</Value>
		</Row>

</Table>
	<Table name="admin_UserCreation">
		<Header>
			<Column name="adminPublisherUserNameOne" type="String" />
			<Column name="adminPublisherUserOnePassword" type="String" />
			<Column name="adminRoleNameOnePublisherUserOne" type="String" />
			<Column name="adminStoreUserNameOne" type="String" />
			<Column name="adminStoreUserOnePassword" type="String" />
			<Column name="adminRoleNameOneStoreUserOne" type="String" />
			<Column name="adminPublisherUserNameTwo" type="String" />
			<Column name="adminPublisherUserTwoPassword" type="String" />
			<Column name="adminRoleNameOnePublisherUserTwo" type="String" />
			<Column name="adminPublisherUserNameThree" type="String" />
			<Column name="adminPublisherUserThreePassword" type="String" />
			<Column name="adminRoleNameOnePublisherUserThree" type="String" />
			<Column name="adminStoreUserNameTwo" type="String" />
			<Column name="adminStoreUserTwoPassword" type="String" />
			<Column name="adminRoleNameOneStoreUserTwo" type="String" />
			<Column name="adminRoleNameSpecialStoreOne" type="String" />
			<Column name="adminStoreUserNameThree" type="String" />
			<Column name="adminStoreUserThreePassword" type="String" />
			<Column name="adminStoreUserNameFour" type="String" />
			<Column name="adminStoreUserFourPassword" type="String" />
			<Column name="storeRoleNameFour" type="String" />
			<Column name="adminStoreUserNameFive" type="String" />
			<Column name="adminStoreUserFivePassword" type="String" />
			<Column name="storeRoleNameFive" type="String" />
			<Column name="adminStoreUserNameSix" type="String" />
			<Column name="adminStoreUserSixPassword" type="String" />
			<Column name="storeRoleNameSix" type="String" />
			<Column name="adminStoreUserNameSeven" type="String" />
			<Column name="adminStoreUserSevenPassword" type="String" />
			<Column name="twoSeconds" type="String" />
			<Column name="fourSeconds" type="String" />
			<Column name="sixSeconds" type="String" />
			<Column name="eightSeconds" type="String" />
		</Header>
		<Row>
			<Value>adminp1</Value>
			<Value>111111</Value>
			<Value>ap1r1</Value>
			<Value>as1</Value>
			<Value>111111</Value>
			<Value>as1r1</Value>
			<Value>ap2</Value>
			<Value>111111</Value>
			<Value>ap2r1</Value>
			<Value>ap3</Value>
			<Value>111111</Value>
			<Value>ap3r1</Value>
			<Value>as2</Value>
			<Value>111111</Value>
			<Value>as2r1</Value>
			<Value>aspecialstore</Value>
			<Value>as3</Value>
			<Value>111111</Value>
			<Value>as4</Value>
			<Value>111111</Value>
			<Value>as4r4</Value>
			<Value>as5</Value>
			<Value>111111</Value>
			<Value>as5r5</Value>
			<Value>as6</Value>
			<Value>111111</Value>
			<Value>as6r6</Value>
			<Value>as7</Value>
			<Value>111111</Value>
			<Value>2000</Value>
			<Value>4000</Value>
			<Value>6000</Value>
			<Value>8000</Value>
		</Row>

</Table>
	<Table name="tenantCreation">
		<Header>
			<Column name="tenantOneDomainName" type="String" />
			<Column name="tenantOneFirstName" type="String" />
			<Column name="tenantOneLastName" type="String" />
			<Column name="adminUsernameTenantOne" type="String" />
			<Column name="adminPasswordTenantOne" type="String" />
			<Column name="emailAddressTenantDomainOne" type="String" />
			<Column name="tenantTwoDomainName" type="String" />
			<Column name="tenantTwoFirstName" type="String" />
			<Column name="tenantTwoLastName" type="String" />
			<Column name="adminUsernameTenantTwo" type="String" />
			<Column name="adminPasswordTenantTwo" type="String" />
			<Column name="emailAddressTenantDomainTwo" type="String" />
			<Column name="tenantThreeDomainName" type="String" />
			<Column name="tenantThreeFirstName" type="String" />
			<Column name="tenantThreeLastName" type="String" />
			<Column name="adminUsernameTenantThree" type="String" />
			<Column name="adminPasswordTenantThree" type="String" />
			<Column name="emailAddressTenantDomainThree" type="String" />
			<Column name="twoSeconds" type="String" />
			<Column name="fourSeconds" type="String" />
			<Column name="sixSeconds" type="String" />
			<Column name="eightSeconds" type="String" />
		</Header>
		<Row>
			<Value>domain_one.com</Value>
			<Value>t1fn</Value>
			<Value>t1ln</Value>
			<Value>t1user</Value>
			<Value>111111</Value>
			<Value>are@gmail.com</Value>
			<Value>domain_two.com</Value>
			<Value>t2fn</Value>
			<Value>t2ln</Value>
			<Value>t2user</Value>
			<Value>111111</Value>
			<Value>dinesh@gmail.com</Value>
			<Value>domain_three.com</Value>
			<Value>t3fn</Value>
			<Value>t3ln</Value>
			<Value>t3user</Value>
			<Value>111111</Value>
			<Value>adam@gmail.com</Value>
			<Value>2000</Value>
			<Value>4000</Value>
			<Value>6000</Value>
			<Value>8000</Value>
		</Row>

</Table>
	<Table name="APILifecycleManagement_APIStates_Deprecated">
		<Header>
			<Column name="APIName" type="String" />
			<Column name="APIContext" type="String" />
			<Column name="APIVersion" type="String" />
			<Column name="tagName" type="String" />
			<Column name="productionEndPoint" type="String" />
			<Column name="sandBoxEndpoint" type="String" />
			<Column name="APIStatePublished" type="String" />
			<Column name="tenantOrAdmin" type="String" />
			<Column name="tenantOrAdminStoreOne" type="String" />
			<Column name="adminOrTenantOneStoreUserOne" type="String" />
			<Column name="adminOrTenantOneStoreUserOnePassword" type="String" />
			<Column name="defaultApplication" type="String" />
			<Column name="tenantOrAdminPublisherOne" type="String" />
			<Column name="adminOrTenantOnePublisherUserOne" type="String" />
			<Column name="adminOrTenantOnePublisherOnePassword" type="String" />
			<Column name="APIStateDeprecated" type="String" />
			<Column name="numberOfUsersZero" type="String" />
			<Column name="tenantOrAdminStoreTwo" type="String" />
			<Column name="yes" type="String" />
			<Column name="no" type="String" />
			<Column name="APIvisibility" type="String" />
			<Column name="urlPatternForPostAndPut" type="String" />
			<Column name="urlPatternForGetDeleteAndHead" type="String" />
			<Column name="numberOfUsersOne" type="String" />
			<Column name="keyTypeToInvokeProduction" type="String" />
			<Column name="keyTypeToInvokeSandBox" type="String" />
			<Column name="buttonNamePost" type="String" />
			<Column name="postPayloadContext" type="String" />
			<Column name="CustomerNameOne" type="String" />
			<Column name="CustomerNameTwo" type="String" />
			<Column name="ResponseCodeTwoHundred" type="String" />
			<Column name="ResponseHeaders" type="String" />
			<Column name="buttonNameGet" type="String" />
			<Column name="buttonNamePut" type="String" />
			<Column name="ResponseBodyNoContent" type="String" />
			<Column name="buttonNameHead" type="String" />
			<Column name="ResponseHeadersNull" type="String" />
			<Column name="buttonNameDelete" type="String" />
			<Column name="deleteResponseHeaders" type="String" />
			<Column name="ResponCodeTwoHundredAndFourForDeleteVerification" type="String" />
		</Header>
		<Row>
			<Value>API</Value>
			<Value>sample_context</Value>
			<Value>1.3.</Value>
			<Value>sample_tag</Value>
			<Value>http://localhost:9763/jaxrs_basic/services/customers</Value>
			<Value>http://localhost:9763/jaxrs_basic/services/customers</Value>
			<Value>PUBLISHED</Value>
			<Value>Admin</Value>
			<Value>AdminStoreOne</Value>
			<Value>keyAdminStoreUserOne</Value>
			<Value>keyAdminStoreUserOnePassword</Value>
			<Value>DefaultApplication</Value>
			<Value>AdminPublisherOne</Value>
			<Value>keyAdminPublisherUserOne</Value>
			<Value>keyAdminPublisherUserOnePassword</Value>
			<Value>DEPRECATED</Value>
			<Value>0</Value>
			<Value>AdminStoreTwo</Value>
			<Value>yes</Value>
			<Value>no</Value>
			<Value>index=0</Value>
			<Value>/customerservice/customers</Value>
			<Value>/customerservice/customers/{id}</Value>
			<Value>1</Value>
			<Value>Production</Value>
			<Value>Sandbox</Value>
			<Value>post</Value>
			<Value>{\&quot;Customer\&quot;:{\&quot;name\&quot;:\&quot;Shiromalie\&quot;}}</Value>
			<Value>Evanthika</Value>
			<Value>Shiromalie</Value>
			<Value>200</Value>
			<Value>application/json</Value>
			<Value>get</Value>
			<Value>put</Value>
			<Value>no content</Value>
			<Value>head</Value>
			<Value>null</Value>
			<Value>delete</Value>
			<Value>application/octet-stream</Value>
			<Value>204</Value>
		</Row>
		<Row>
			<Value>API</Value>
			<Value>sample_context</Value>
			<Value>1.3.</Value>
			<Value>sample_tag</Value>
			<Value>http://localhost:9763/jaxrs_basic/services/customers</Value>
			<Value>http://localhost:9763/jaxrs_basic/services/customers</Value>
			<Value>PUBLISHED</Value>
			<Value>TenantOne</Value>
			<Value>TenantOneStoreOne</Value>
			<Value>keyTenantOneStoreUserOne</Value>
			<Value>keyTenantOneStoreUserOnePassword</Value>
			<Value>DefaultApplication</Value>
			<Value>TenantOnePublisherOne</Value>
			<Value>keyTenantOnePublisherUserOne</Value>
			<Value>keyTenantOnePublisherOnePassword</Value>
			<Value>DEPRECATED</Value>
			<Value>0</Value>
			<Value>TenantOneStoreTwo</Value>
			<Value>yes</Value>
			<Value>no</Value>
			<Value>index=0</Value>
			<Value>/customerservice/customers</Value>
			<Value>/customerservice/customers/{id}</Value>
			<Value>1</Value>
			<Value>Production</Value>
			<Value>Sandbox</Value>
			<Value>post</Value>
			<Value>{\&quot;Customer\&quot;:{\&quot;name\&quot;:\&quot;Shiromalie\&quot;}}</Value>
			<Value>Evanthika</Value>
			<Value>Shiromalie</Value>
			<Value>200</Value>
			<Value>application/json</Value>
			<Value>get</Value>
			<Value>put</Value>
			<Value>no content</Value>
			<Value>head</Value>
			<Value>null</Value>
			<Value>delete</Value>
			<Value>application/octet-stream</Value>
			<Value>204</Value>
		</Row>

</Table>
	<Table name="scope">
		<Header>
			<Column name="domain" type="String" />
			<Column name="adminOrTenantOnePublisherUserOne" type="String" />
			<Column name="adminOrTenantOnePublisherOnePassword" type="String" />
			<Column name="APIImagePath" type="String" />
			<Column name="ProductionEndPontJaxRS" type="String" />
			<Column name="sandboxEndPointJaxRS" type="String" />
			<Column name="URLPattern" type="String" />
			<Column name="verbMethodGET" type="String" />
			<Column name="verbMethodPOST" type="String" />
			<Column name="verbMethodPUT" type="String" />
			<Column name="verbMethodDELETE" type="String" />
			<Column name="userAdmin" type="String" />
			<Column name="AdminPasswd" type="String" />
			<Column name="roleName" type="String" />
			<Column name="scopeKeyOne" type="String" />
			<Column name="tag" type="String" />
			<Column name="scopeNameOne" type="String" />
			<Column name="scopeKeyTwo" type="String" />
			<Column name="scopeNameTwo" type="String" />
			<Column name="scopeKeyThree" type="String" />
			<Column name="scopeNameThree" type="String" />
			<Column name="scopeKeyFour" type="String" />
			<Column name="scopeNameFour" type="String" />
			<Column name="InvalidKey" type="String" />
			<Column name="ScopeDescription" type="String" />
			<Column name="ScopeKeyFive" type="String" />
			<Column name="ScopeNameFive" type="String" />
			<Column name="ScopeKeySix" type="String" />
			<Column name="ScopeNameSix" type="String" />
			<Column name="scopeKeySeven" type="String" />
			<Column name="scopeNameSeven" type="String" />
			<Column name="APIName" type="String" />
			<Column name="APIContest" type="String" />
		</Header>
		<Row>
			<Value>Tenant</Value>
			<Value>keyTenantOnePublisherUserOne</Value>
			<Value>keyTenantOnePublisherOnePassword</Value>
			<Value>test.jpg</Value>
			<Value>http://appserver/resource</Value>
			<Value>http://appserver/resource</Value>
			<Value>/view/{@,#}/test/{^,_}/test1</Value>
			<Value>get</Value>
			<Value>post</Value>
			<Value>put</Value>
			<Value>delete</Value>
			<Value>admin</Value>
			<Value>admin</Value>
			<Value>role2</Value>
			<Value>keyOne</Value>
			<Value>def</Value>
			<Value>ScopeNameOne</Value>
			<Value>keyTwo</Value>
			<Value>ScopeNameTwo</Value>
			<Value>keyThree</Value>
			<Value>ScopeNameThree</Value>
			<Value>keyFour</Value>
			<Value>ScopeNameFour</Value>
			<Value>http://appserver/resource</Value>
			<Value>dfgdfgdfgdgfd</Value>
			<Value>keyFive</Value>
			<Value>ScopeNameFive</Value>
			<Value>keySix</Value>
			<Value>ScopeNameSix</Value>
			<Value>keySeven</Value>
			<Value>ScopeNameSeven</Value>
			<Value>binaradz</Value>
			<Value>/fdd</Value>
		</Row>
		<Row>
			<Value>carbon.super</Value>
			<Value>keyAdminPublisherUserOne</Value>
			<Value>keyAdminPublisherUserOnePassword</Value>
			<Value>test.jpg</Value>
			<Value>http://appserver/resource</Value>
			<Value>http://appserver/resource</Value>
			<Value>/view/{@,#}/test/{^,_}/test2</Value>
			<Value>get</Value>
			<Value>post</Value>
			<Value>put</Value>
			<Value>delete</Value>
			<Value>admin</Value>
			<Value>admin</Value>
			<Value>role3</Value>
			<Value>keyOne</Value>
			<Value>def</Value>
			<Value>ScopeNameOne</Value>
			<Value>keyTwo</Value>
			<Value>ScopeNameTwo</Value>
			<Value>keyThree</Value>
			<Value>ScopeNameThree</Value>
			<Value>keyFour</Value>
			<Value>ScopeNameFour</Value>
			<Value>http://appserver/resource</Value>
			<Value>dfgdfgdfgdgfd</Value>
			<Value>keyFive</Value>
			<Value>ScopeNameFive</Value>
			<Value>keySix</Value>
			<Value>ScopeNameSix</Value>
			<Value>keySeven</Value>
			<Value>ScopeNameSeven</Value>
			<Value>binaradz</Value>
			<Value>/fdd</Value>
		</Row>

</Table>
































</DataTables>